crg_templates/__init__.py
crg_templates-0.0.1.dist-info/LICENSE
crg_templates-0.0.1.dist-info/METADATA
crg_templates-0.0.1.dist-info/WHEEL
crg_templates-0.0.1.dist-info/top_level.txt
crg_templates-0.0.1.dist-info/RECORD
