Metadata-Version: 2.1
Name: crg-templates
Version: 0.0.1
Summary: Provides templates for crg
Home-page: UNKNOWN
Author: Anti Räis
Author-email: antirais@gmail.com
License: MIT
Platform: any
Classifier: Development Status :: 3 - Alpha
Classifier: Intended Audience :: Developers
Classifier: License :: OSI Approved :: MIT License
Classifier: Operating System :: OS Independent
Classifier: Programming Language :: Python
Classifier: Programming Language :: Python :: 3.6
Classifier: Programming Language :: Python :: 3.7
Classifier: Topic :: Software Development :: Libraries :: Python Modules
Requires-Python: >= 3.6
